MANIFEST.in
README.rst
pyproject.toml
setup.cfg
setup.py
docs/info.txt
employee/__init__.py
employee/admin.py
employee/apps.py
employee/forms.py
employee/models.py
employee/tests.py
employee/urls.py
employee/utils.py
employee/views.py
employee/migrations/0001_initial.py
employee/migrations/__init__.py
employee/templates/employee/add.html
employee/templates/employee/dashboard.html
employee/templates/employee/detail.html
employee/templates/employee/detail_left.html
employee/templates/employee/detail_right.html
employee/templates/employee/list_sec.html
employee/templates/employee/list_xefe.html
employee/templates/employee/main.html
employee/templates/employee/sidebard.html
employee/templates/user/account.html
employee/templates/user/change_password.html
employee/templates/user/change_password_done.html
maetl_employee.egg-info/PKG-INFO
maetl_employee.egg-info/SOURCES.txt
maetl_employee.egg-info/dependency_links.txt
maetl_employee.egg-info/requires.txt
maetl_employee.egg-info/top_level.txt